dseqmap4nlp/__init__.py
dseqmap4nlp/annotationset.py
dseqmap4nlp/basemapper.py
dseqmap4nlp/charmapper.py
dseqmap4nlp/labelloader.py
dseqmap4nlp/raggedmapper.py
dseqmap4nlp/spacymapper.py
dseqmap4nlp-0.0.5.dist-info/LICENSE
dseqmap4nlp-0.0.5.dist-info/METADATA
dseqmap4nlp-0.0.5.dist-info/WHEEL
dseqmap4nlp-0.0.5.dist-info/top_level.txt
dseqmap4nlp-0.0.5.dist-info/RECORD
