Metadata-Version: 2.1
Name: dseqmap4nlp
Version: 0.0.5
Summary: A small tool to parse and process annotated text corpora
Author-email: Johann Frei <johann_frei@yahoo.de>
Project-URL: Homepage, https://github.com/j-frei/DSeqMap4NLP
Project-URL: Issues, https://github.com/j-frei/DSeqMap4NLP/issues
Classifier: Programming Language :: Python :: 3
Classifier: License :: OSI Approved :: MIT License
Classifier: Operating System :: OS Independent
Classifier: Topic :: Scientific/Engineering
Classifier: Topic :: Text Processing
Requires-Python: >=3.8
License-File: LICENSE
Requires-Dist: spacy
